py_mstr/__init__.py
py_mstr/py_mstr.py
tests/__init__.py
tests/test.py
py_mstr-1.0.0.dist-info/LICENSE
py_mstr-1.0.0.dist-info/METADATA
py_mstr-1.0.0.dist-info/WHEEL
py_mstr-1.0.0.dist-info/top_level.txt
py_mstr-1.0.0.dist-info/RECORD
