Metadata-Version: 2.1
Name: py-mstr
Version: 1.0.0
Summary: Python API for Microstrategy Web Tasks
Home-page: http://github.com/infoscout/py-mstr
Author: InfoScout
Author-email: oss@infoscoutinc.com
License: MIT
Platform: UNKNOWN
Classifier: Intended Audience :: Developers
Classifier: License :: OSI Approved
Classifier: License :: OSI Approved :: MIT License
Classifier: Operating System :: OS Independent
Classifier: Programming Language :: Python
Classifier: Programming Language :: Python :: 2.7
Classifier: Topic :: Software Development :: Libraries
Requires-Dist: pyquery (<1.3.0,>=1.2.8)
Requires-Dist: requests (>=2.3.0)
